rsa/__init__.py
rsa/_compat.py
rsa/asn1.py
rsa/cli.py
rsa/common.py
rsa/core.py
rsa/key.py
rsa/parallel.py
rsa/pem.py
rsa/pkcs1.py
rsa/pkcs1_v2.py
rsa/prime.py
rsa/randnum.py
rsa/transform.py
rsa/util.py
rsa-4.7.1.dist-info/DESCRIPTION.rst
rsa-4.7.1.dist-info/LICENSE.txt
rsa-4.7.1.dist-info/METADATA
rsa-4.7.1.dist-info/RECORD
rsa-4.7.1.dist-info/WHEEL
rsa-4.7.1.dist-info/entry_points.txt
rsa-4.7.1.dist-info/metadata.json
rsa-4.7.1.dist-info/top_level.txt
