Metadata-Version: 2.1
Name: rsa
Version: 4.7.1
Summary: Pure-Python RSA implementation
Home-page: https://stuvel.eu/rsa
Author: Sybren A. Stuvel
Author-email: sybren@stuvel.eu
Maintainer: Sybren A. Stuvel
Maintainer-email: sybren@stuvel.eu
License: ASL 2
Platform: UNKNOWN
Classifier: Development Status :: 5 - Production/Stable
Classifier: Intended Audience :: Developers
Classifier: Intended Audience :: Education
Classifier: Intended Audience :: Information Technology
Classifier: License :: OSI Approved :: Apache Software License
Classifier: Operating System :: OS Independent
Classifier: Programming Language :: Python
Classifier: Programming Language :: Python :: 3
Classifier: Programming Language :: Python :: 3.5
Classifier: Programming Language :: Python :: 3.6
Classifier: Programming Language :: Python :: 3.7
Classifier: Programming Language :: Python :: 3.8
Classifier: Programming Language :: Python :: 3.9
Classifier: Programming Language :: Python :: Implementation :: CPython
Classifier: Programming Language :: Python :: Implementation :: PyPy
Classifier: Topic :: Security :: Cryptography
Requires-Python: >=3.5, <4
